{
  "id": "COURSE-ESHRAM-001",
  "quantity": { "maximum": { "count": 1 } },
  "descriptor": {
    "name": "e-Shram Card Registration Facilitator",
    "short_desc": "Learn to register unorganized sector workers on the e-Shram portal for social security benefits.",
    "long_desc": "<p><strong>Course Overview:</strong><br>This course trains agents on the end-to-end process of e-Shram card registration. It covers identifying unorganized workers, the documents required, the online registration process, and explaining the benefits linked to the e-Shram UAN card, such as accident insurance.</p>",
    "images": [{ "url": "https://i.ibb.co/hCKqJgD/e-shram-logo.png" }]
  },
  "creator": {
    "descriptor": { "name": "Haqdarshak Social Security Division" }
  },
  "price": { "currency": "INR", "value": "0" },
  "category_ids": ["GOV-SCHEMES-SOCIAL-SECURITY", "GOV-SCHEMES-LIVELIHOOD"],
  "rating": "4.8",
  "rateable": true,
  "keywords": [
    "eshram",
    "e-shram",
    "shramik card",
    "uan card",
    "unorganized worker",
    "mazdoor"
  ],
  "tags": [
    {
      "descriptor": { "code": "scheme-metadata", "name": "Scheme Metadata" },
      "list": [
        { "descriptor": { "code": "learner-level" }, "value": "Beginner" },
        {
          "descriptor": { "code": "scheme-type" },
          "value": "Social Security Registration"
        },
        {
          "descriptor": { "code": "target-audience" },
          "value": "Construction workers, gig workers, domestic workers, street vendors"
        },
        { "descriptor": { "code": "course-duration" }, "value": "P2H" }
      ]
    }
  ]
}
